python_webex/__init__.py
python_webex/v1/Bot.py
python_webex/v1/Card.py
python_webex/v1/Message.py
python_webex/v1/People.py
python_webex/v1/Room.py
python_webex/v1/Webhook.py
python_webex/v1/__init__.py
python_webex/webhook/__init__.py
python_webex/webhook/handlers.py
python_webex_bot-0.901.data/scripts/python_webex_bot
python_webex_bot-0.901.dist-info/LICENSE
python_webex_bot-0.901.dist-info/METADATA
python_webex_bot-0.901.dist-info/WHEEL
python_webex_bot-0.901.dist-info/top_level.txt
python_webex_bot-0.901.dist-info/RECORD
