Metadata-Version: 2.1
Name: python-webex-bot
Version: 0.901
Summary: Enable sending markdown in messges
Home-page: https://github.com/Paul-weqe/python_webex_bot
Author: Paul-weqe
Author-email: paul1tw1@gmail.com
License: UNKNOWN
Platform: UNKNOWN
Classifier: Programming Language :: Python :: 3
Classifier: License :: OSI Approved :: MIT License
Classifier: Operating System :: OS Independent
License-File: LICENSE
Requires-Dist: Flask
Requires-Dist: Jinja2
Requires-Dist: MarkupSafe
Requires-Dist: Werkzeug
Requires-Dist: certifi
Requires-Dist: chardet
Requires-Dist: click
Requires-Dist: idna
Requires-Dist: itsdangerous
Requires-Dist: requests
Requires-Dist: urllib3
